Metadata-Version: 2.1
Name: GeoFake
Version: 0.0.1
Summary: This is a fake project to get lab credit for GEOG 510
Home-page: https://github.com/whitson-buck/GeoFake
Author: Whitson Buck
Author-email: whitsonbuck@gmail.com
License: MIT license
Keywords: geofake
Classifier: Development Status :: 2 - Pre-Alpha
Classifier: Intended Audience :: Developers
Classifier: License :: OSI Approved :: MIT License
Classifier: Natural Language :: English
Classifier: Programming Language :: Python :: 3
Classifier: Programming Language :: Python :: 3.7
Classifier: Programming Language :: Python :: 3.8
Classifier: Programming Language :: Python :: 3.9
Classifier: Programming Language :: Python :: 3.10
Requires-Python: >=3.7
License-File: LICENSE
